fastapi_app_plus/__init__.py
fastapi_app_plus/app_plus.py
fastapi_app_plus/static/css/swagger-ui.css
fastapi_app_plus/static/js/redoc.standalone.js
fastapi_app_plus/static/js/swagger-ui-bundle.js
fastapi_app_plus-0.1.1.dist-info/LICENSE
fastapi_app_plus-0.1.1.dist-info/METADATA
fastapi_app_plus-0.1.1.dist-info/WHEEL
fastapi_app_plus-0.1.1.dist-info/top_level.txt
fastapi_app_plus-0.1.1.dist-info/RECORD
