Metadata-Version: 2.2
Name: fastapi-app-plus
Version: 0.1.1
Summary: The extended function library of fastapi can be read README.md
Home-page: https://github.com/hgz1989/fastapi-app-plus
Author: HanGuangZheng
Author-email: hanguangzheng@qq.com
Classifier: Programming Language :: Python :: 3
Classifier: License :: OSI Approved :: MIT License
Classifier: Operating System :: OS Independent
Requires-Python: >=3.8
License-File: LICENSE
Requires-Dist: fastapi>=0.111.0
